README.md
setup.py
domino_python.egg-info/PKG-INFO
domino_python.egg-info/SOURCES.txt
domino_python.egg-info/dependency_links.txt
domino_python.egg-info/entry_points.txt
domino_python.egg-info/requires.txt
domino_python.egg-info/top_level.txt
src/__init__.py
src/constants.py
src/runner.py
src/core/__init__.py
src/core/domino.py
src/core/network_builder.py
src/core/preprocess_slices.py
src/data/__init__.py
src/utils/__init__.py
src/utils/ensembl2gene_symbol.py
src/utils/graph_influence_linear_th.py
src/utils/scripts.py
src/utils/visualize_modules.py